Metadata-Version: 1.1
Name: firmware-uploader
Version: 0.4.0
Summary: Uploads firmware to multiple embedded devices.
Home-page: https://github.com/janelia-pypi/firmware_uploader_python
Author: Peter Polidoro
Author-email: peterpolidoro@gmail.com
License: BSD
Platform: UNKNOWN
Classifier: Development Status :: 4 - Beta
Classifier: Intended Audience :: Developers
Classifier: Topic :: Software Development :: Build Tools
Classifier: License :: OSI Approved :: BSD License
Classifier: Programming Language :: Python :: 2.7
Classifier: Programming Language :: Python :: 3
